{
  "date": "2025-05-24",
  "fetchedAt": "2026-02-05T07:27:08.572Z",
  "articleCount": 101,
  "source": "historical-import",
  "articles": [
    {
      "title": "Dubai picks XRP Ledger for real estate tokenization as 3,000 investors register",
      "link": "https://cryptopanic.com/news/ripple/22063014/Dubai-picks-XRP-Ledger-for-real-estate-tokenization-as-3000-investors-register",
      "pubDate": "2025-05-24T22:42:54.000Z",
      "source": "Historical",
      "sourceKey": "historical",
      "category": "altcoin",
      "description": "More than 3,000 investors have registered for Dubai’s flagship real estate tokenization program. Mahmoud AlBurai, a senior executive at the Dubai Land Department (DLD), disclosed this in a post on LinkedIn. According to AlBurai, the massive number of participants who have joined the waitlist highlights their interest in the project. The real estate tokenization project […]",
      "currencies": [
        "XRP"
      ],
      "votes": {
        "positive": 6,
        "negative": 1
      },
      "sentiment": "bullish"
    },
    {
      "title": "Ethereum Stands out Post-Pectra Upgrade as Crypto Inflows Skyrocket to $785 Million",
      "link": "https://cryptopanic.com/news/ethereum/22062506/Ethereum-Stands-out-Post-Pectra-Upgrade-as-Crypto-Inflows-Skyrocket-to-785-Million",
      "pubDate": "2025-05-24T21:04:41.000Z",
      "source": "Historical",
      "sourceKey": "historical",
      "category": "ethereum",
      "description": "Ethereum closed last week on a remarkable note, as weekly inflows skyrocketed to unprecedented levels. Data from leading European alternative asset manager CoinShares revealed that inflows into Ethereum hit $205 million, marking a major increase from the previously reported $1. 5 million. James Butterfill, a researcher at CoinShares, explained that the new development might be directly […]",
      "currencies": [
        "ETH"
      ],
      "votes": {
        "positive": 15,
        "negative": 2
      },
      "sentiment": "bullish"
    },
    {
      "title": "Cardano Price Targets $1.48, Will It Reclaim Bullish Momentum?",
      "link": "https://cryptopanic.com/news/cardano/22062215/Cardano-Price-Targets-148-Will-It-Reclaim-Bullish-Momentum",
      "pubDate": "2025-05-24T20:40:00.000Z",
      "source": "Historical",
      "sourceKey": "historical",
      "category": "trading",
      "description": "Cardano price has gained attention from buyers due to its recent surge after breaking out of a multi-month consolidation phase around the $0. 70 level. The recent break above $0. 80 has triggered positive technical signals for future growth",
      "currencies": [
        "ADA"
      ],
      "votes": {
        "positive": 5,
        "negative": 4
      }
    },
    {
      "title": "Uniswap: $13mln exits Binance as UNI coils – What do whales know?",
      "link": "https://cryptopanic.com/news/uniswap/22061908/Uniswap-13mln-exits-Binance-as-UNI-coils-What-do-whales-know",
      "pubDate": "2025-05-24T20:00:39.000Z",
      "source": "Historical",
      "sourceKey": "historical",
      "category": "defi",
      "description": "NULL",
      "currencies": [
        "UNI"
      ]
    },
    {
      "title": "SHIB Targets 39% Rally, AAVE Gains 22%, Unstaked Raises $7M for AI Agents",
      "link": "https://cryptopanic.com/news/aave/22061253/SHIB-Targets-39-Rally-AAVE-Gains-22-Unstaked-Raises-7M-for-AI-Agents",
      "pubDate": "2025-05-24T18:30:36.000Z",
      "source": "Historical",
      "sourceKey": "historical",
      "category": "defi",
      "description": "NULL",
      "currencies": [
        "SHIB",
        "AAVE"
      ]
    },
    {
      "title": "PEPE, VeChain, or Cold Wallet: Breaking Down the Top Crypto Picks",
      "link": "https://cryptopanic.com/news/vechain/22060945/PEPE-VeChain-or-Cold-Wallet-Breaking-Down-the-Top-Crypto-Picks",
      "pubDate": "2025-05-24T18:00:56.000Z",
      "source": "Historical",
      "sourceKey": "historical",
      "category": "general",
      "description": "NULL",
      "currencies": [
        "VET",
        "PEPE"
      ]
    },
    {
      "title": "Ethereum Holder Sold Over $570 Million in 48 Hours – What’s Next for ETH?",
      "link": "https://cryptopanic.com/news/ethereum/22061235/Ethereum-Holder-Sold-Over-570-Million-in-48-Hours-Whats-Next-for-ETH",
      "pubDate": "2025-05-24T17:30:00.000Z",
      "source": "Historical",
      "sourceKey": "historical",
      "category": "ethereum",
      "description": "Ethereum (ETH) has shown little price movement over the past two weeks despite the broader cryptocurrency market displaying bullish momentum. This stagnation in ETH’s price comes at a time when selling activity has intensified. These factors suggest a cautious short-term outlook for Ethereum as the week continues. Ethereum Investors Secure Their Profits Recent data indicates significant selling pressure on Ethereum",
      "currencies": [
        "ETH"
      ],
      "votes": {
        "positive": 2,
        "negative": 3
      }
    },
    {
      "title": "4 Top Crypto Coins in 2025: Ethereum, Hyperliquid, Monero, & Unstaked Ready to Deliver Huge ROIs!",
      "link": "https://cryptopanic.com/news/monero/22061252/4-Top-Crypto-Coins-in-2025-Ethereum-Hyperliquid-Monero-Unstaked-Ready-to-Deliver-Huge-ROIs",
      "pubDate": "2025-05-24T16:33:15.000Z",
      "source": "Historical",
      "sourceKey": "historical",
      "category": "ethereum",
      "description": "NULL",
      "currencies": [
        "ETH",
        "XMR",
        "HYPE"
      ]
    },
    {
      "title": "Best Crypto Coin to Buy Now: BlockDAG, XRP, Polkadot & NEAR Protocol",
      "link": "https://cryptopanic.com/news/polkadot/22060279/Best-Crypto-Coin-to-Buy-Now-BlockDAG-XRP-Polkadot-NEAR-Protocol",
      "pubDate": "2025-05-24T16:30:36.000Z",
      "source": "Historical",
      "sourceKey": "historical",
      "category": "altcoin",
      "description": "NULL",
      "currencies": [
        "XRP",
        "DOT",
        "NEAR"
      ]
    },
    {
      "title": "Cardano (ADA) Mystery: $1.2 Billion Volume Despite Price Drop",
      "link": "https://cryptopanic.com/news/cardano/22060190/Cardano-ADA-Mystery-12-Billion-Volume-Despite-Price-Drop",
      "pubDate": "2025-05-24T16:14:00.000Z",
      "source": "Historical",
      "sourceKey": "historical",
      "category": "trading",
      "description": "ADA price dropped nearly 4%",
      "currencies": [
        "ADA"
      ],
      "votes": {
        "positive": 3,
        "negative": 2
      }
    },
    {
      "title": "Top Performing Cryptos Today: BlockDAG, Tron, Polygon, & DOT",
      "link": "https://cryptopanic.com/news/polkadot/22059623/Top-Performing-Cryptos-Today-BlockDAG-Tron-Polygon-DOT",
      "pubDate": "2025-05-24T16:00:39.000Z",
      "source": "Historical",
      "sourceKey": "historical",
      "category": "layer2",
      "description": "NULL",
      "currencies": [
        "DOT",
        "TRX",
        "MATIC"
      ]
    },
    {
      "title": "Spell Wallet Daily Puzzle 25 May 2025: Earn Reward of 1 MANA",
      "link": "https://cryptopanic.com/news/decentraland/22060216/Spell-Wallet-Daily-Puzzle-25-May-2025-Earn-Reward-of-1-MANA",
      "pubDate": "2025-05-24T14:30:00.000Z",
      "source": "Historical",
      "sourceKey": "historical",
      "category": "stablecoin",
      "description": "NULL",
      "currencies": [
        "MANA"
      ]
    },
    {
      "title": "Germany Sold 50,000 Bitcoin Seized from Movie2K for $2.88 Billion at $57,600 Each; Bitcoin Price Doubled Since to $5.5 Billion",
      "link": "https://cryptopanic.com/news/bitcoin/22058296/Germany-Sold-50000-Bitcoin-Seized-from-Movie2K-for-288-Billion-at-57600-Each-Bitcoin-Price-Doubled-Since-to-55-Billion",
      "pubDate": "2025-05-24T13:35:18.000Z",
      "source": "Historical",
      "sourceKey": "historical",
      "category": "bitcoin",
      "description": "NULL",
      "currencies": [
        "BTC"
      ]
    },
    {
      "title": "Bitcoin could hit $200K by year-end 2025, says TradingShot: Analysts cite historical patterns and bullish momentum",
      "link": "https://cryptopanic.com/news/bitcoin/22057507/Bitcoin-could-hit-200K-by-year-end-2025-says-TradingShot-Analysts-cite-historical-patterns-and-bullish-momentum",
      "pubDate": "2025-05-24T12:32:57.000Z",
      "source": "Historical",
      "sourceKey": "historical",
      "category": "bitcoin",
      "description": "24-5-2025 – As Bitcoin (BTC) scales new peaks, shattering records with a recent high above $111,000, a wave of optimism ripples through the cryptocurrency market. TradingShot, a respected voice in trading circles, has ignited excitement with a compelling forecast: Bitcoin could soar to $200,000 by the close of 2025, a prediction rooted in meticulous analysis [. .",
      "currencies": [
        "BTC"
      ],
      "votes": {
        "positive": 6,
        "negative": 0
      },
      "sentiment": "bullish"
    },
    {
      "title": "Scaramucci Predicts Solana Adoption by Major Players: Details",
      "link": "https://cryptopanic.com/news/solana/22056548/Scaramucci-Predicts-Solana-Adoption-by-Major-Players-Details",
      "pubDate": "2025-05-24T11:14:00.000Z",
      "source": "Historical",
      "sourceKey": "historical",
      "category": "altcoin",
      "description": "Solana to become rail system for stocks and bonds, says Anthony Scaramucci",
      "currencies": [
        "SOL"
      ],
      "votes": {
        "positive": 3,
        "negative": 3
      }
    },
    {
      "title": "ICP HUB Canada & US Wraps Up High-Impact Week Across Canada Crypto Week 2025",
      "link": "https://cryptopanic.com/news/internet-computer/22056102/ICP-HUB-Canada-US-Wraps-Up-High-Impact-Week-Across-Canada-Crypto-Week-2025",
      "pubDate": "2025-05-24T11:06:33.000Z",
      "source": "Historical",
      "sourceKey": "historical",
      "category": "altcoin",
      "description": "NULL",
      "currencies": [
        "ICP"
      ]
    },
    {
      "title": "AAVE whale’s $15 mln buy points to recovery – Can it hold $270?",
      "link": "https://cryptopanic.com/news/aave/22055866/AAVE-whales-15-mln-buy-points-to-recovery-Can-it-hold-270",
      "pubDate": "2025-05-24T11:00:05.000Z",
      "source": "Historical",
      "sourceKey": "historical",
      "category": "defi",
      "description": "NULL",
      "currencies": [
        "AAVE"
      ]
    },
    {
      "title": "If History Repeats Bitcoin Could be on the Verge of its Strongest Growth Cycle Yet",
      "link": "https://cryptopanic.com/news/bitcoin/22054859/If-History-Repeats-Bitcoin-Could-be-on-the-Verge-of-its-Strongest-Growth-Cycle-Yet",
      "pubDate": "2025-05-24T10:00:12.000Z",
      "source": "Historical",
      "sourceKey": "historical",
      "category": "bitcoin",
      "description": "According to Bitwise, institutional inflows into BTC could reach $180 billion by 2026, driven by a wave of demand from […] The post If History Repeats Bitcoin Could be on the Verge of its Strongest Growth Cycle Yet appeared first on Coindoo.",
      "currencies": [
        "BTC"
      ],
      "votes": {
        "positive": 5,
        "negative": 0
      },
      "sentiment": "bullish"
    },
    {
      "title": "Ethereum Crypto Getting Closer to $3000 Mark: Best Ethereum Crypto to Buy Now",
      "link": "https://cryptopanic.com/news/ethereum/22054835/Ethereum-Crypto-Getting-Closer-to-3000-Mark-Best-Ethereum-Crypto-to-Buy-Now",
      "pubDate": "2025-05-24T09:40:05.000Z",
      "source": "Historical",
      "sourceKey": "historical",
      "category": "ethereum",
      "description": "Are you wondering what the best crypto to buy on the ETH network is? It seems that things are heating up for the project. has gained traction with an impressive 43% surge for the past 30 days. This has sparked many conversations in the crypto community, and people are looking for a strategic buy to.",
      "currencies": [
        "ETH"
      ],
      "votes": {
        "positive": 12,
        "negative": 1
      },
      "sentiment": "bullish"
    },
    {
      "title": "XRP’s Trump-Era Comeback: Can $25K in XRP Make You a Millionaire?",
      "link": "https://cryptopanic.com/news/ripple/22054815/XRPs-Trump-Era-Comeback-Can-25K-in-XRP-Make-You-a-Millionaire",
      "pubDate": "2025-05-24T09:23:00.000Z",
      "source": "Historical",
      "sourceKey": "historical",
      "category": "altcoin",
      "description": "Can $25K in XRP make you a millionaire? Since the election, XRP has surged on investor confidence, the end of the SEC lawsuit, and speculation around an ETF. <p>The post XRP’s Trump-Era Comeback: Can $25K in XRP Make You a Millionaire? first appeared on Ecoinimist. </p>",
      "currencies": [
        "XRP"
      ],
      "votes": {
        "positive": 2,
        "negative": 5
      },
      "sentiment": "bearish"
    },
    {
      "title": "XRP Adoption Booms in Singapore! 2025 Crypto Report Reveals Shocking Surge",
      "link": "https://cryptopanic.com/news/22053052/XRP-Adoption-Booms-in-Singapore-2025-Crypto-Report-Reveals-Shocking-Surge?mtm_campaign=API-OFA",
      "pubDate": "2025-05-24T07:38:26.000Z",
      "source": "Historical",
      "sourceKey": "historical",
      "category": "trading",
      "description": "NULL",
      "currencies": [
        "XRP",
        "RLUSD"
      ]
    },
    {
      "title": "Kraken Officially Lists Pi Network Perpetual Futures With Up to 20x Leverage",
      "link": "https://cryptopanic.com/news/22053037/Kraken-Officially-Lists-Pi-Network-Perpetual-Futures-With-Up-to-20x-Leverage?mtm_campaign=API-OFA",
      "pubDate": "2025-05-24T07:31:48.000Z",
      "source": "Historical",
      "sourceKey": "historical",
      "category": "exchange",
      "description": "NULL",
      "currencies": [
        "PI"
      ]
    },
    {
      "title": "Tesla’s Bitcoin holdings are now worth more than $1.25B",
      "link": "https://cryptopanic.com/news/22052648/Teslas-Bitcoin-holdings-are-now-worth-more-than-125B?mtm_campaign=API-OFA",
      "pubDate": "2025-05-24T07:07:14.000Z",
      "source": "Historical",
      "sourceKey": "historical",
      "category": "bitcoin",
      "description": "NULL",
      "currencies": [
        "BTC"
      ]
    },
    {
      "title": "Jupiter’s rally gains strength: Will JUP bulls target the $0.75 mark?",
      "link": "https://cryptopanic.com/news/22052184/Jupiters-rally-gains-strength-Will-JUP-bulls-target-the-075-mark?mtm_campaign=API-OFA",
      "pubDate": "2025-05-24T07:00:22.000Z",
      "source": "Historical",
      "sourceKey": "historical",
      "category": "trading",
      "description": "NULL",
      "currencies": [
        "JUP",
        "OI"
      ]
    },
    {
      "title": "Judge overturns fraud convictions in Mango Markets exploit case",
      "link": "https://cryptopanic.com/news/22052380/Judge-overturns-fraud-convictions-in-Mango-Markets-exploit-case?mtm_campaign=API-OFA",
      "pubDate": "2025-05-24T07:00:16.000Z",
      "source": "Historical",
      "sourceKey": "historical",
      "category": "general",
      "description": "NULL",
      "currencies": [
        "MNGO"
      ]
    },
    {
      "title": "Trump Hosts Exclusive $TRUMP Coin Dinner at Golf Club",
      "link": "https://cryptopanic.com/news/22052183/Trump-Hosts-Exclusive-TRUMP-Coin-Dinner-at-Golf-Club?mtm_campaign=API-OFA",
      "pubDate": "2025-05-24T06:55:23.000Z",
      "source": "Historical",
      "sourceKey": "historical",
      "category": "general",
      "description": "NULL",
      "currencies": [
        "TRUMP"
      ]
    },
    {
      "title": "Michigan lawmakers push new crypto bills covering BTC mining, CBDCs, and retirement funds",
      "link": "https://cryptopanic.com/news/22052135/Michigan-lawmakers-push-new-crypto-bills-covering-BTC-mining-CBDCs-and-retirement-funds?mtm_campaign=API-OFA",
      "pubDate": "2025-05-24T06:30:43.000Z",
      "source": "Historical",
      "sourceKey": "historical",
      "category": "bitcoin",
      "description": "NULL",
      "currencies": [
        "BTC"
      ]
    },
    {
      "title": "Crypto Market Could See Weeks of Bullish Momentum Ahead Before Market Cools",
      "link": "https://cryptopanic.com/news/22052136/Crypto-Market-Could-See-Weeks-of-Bullish-Momentum-Ahead-Before-Market-Cools?mtm_campaign=API-OFA",
      "pubDate": "2025-05-24T06:30:33.000Z",
      "source": "Historical",
      "sourceKey": "historical",
      "category": "trading",
      "description": "NULL",
      "currencies": [
        "PEPE"
      ]
    },
    {
      "title": "‘More Than a Co-Founder, You’r e a Brother’, Says Polygon’s Sandeep Nailwal as Mihailo Bjelic Steps Down",
      "link": "https://cryptopanic.com/news/22052126/More-Than-a-Co-Founder-Your-e-a-Brother-Says-Polygons-Sandeep-Nailwal-as-Mihailo-Bjelic-Steps-Down?mtm_campaign=API-OFA",
      "pubDate": "2025-05-24T06:27:01.000Z",
      "source": "Historical",
      "sourceKey": "historical",
      "category": "layer2",
      "description": "NULL",
      "currencies": [
        "ETH"
      ]
    },
    {
      "title": "White House Crypto Czar to Speak at Bitcoin 2025 Conference",
      "link": "https://cryptopanic.com/news/22052127/White-House-Crypto-Czar-to-Speak-at-Bitcoin-2025-Conference?mtm_campaign=API-OFA",
      "pubDate": "2025-05-24T06:25:43.000Z",
      "source": "Historical",
      "sourceKey": "historical",
      "category": "bitcoin",
      "description": "NULL",
      "currencies": [
        "BTC"
      ]
    },
    {
      "title": "Bitcoin Price Crashes to $106,750 – Key Levels Watch as Trump Revives Tariff War",
      "link": "https://cryptopanic.com/news/22052105/Bitcoin-Price-Crashes-to-106750-Key-Levels-Watch-as-Trump-Revives-Tariff-War?mtm_campaign=API-OFA",
      "pubDate": "2025-05-24T06:16:48.000Z",
      "source": "Historical",
      "sourceKey": "historical",
      "category": "bitcoin",
      "description": "NULL",
      "currencies": [
        "BTC"
      ]
    },
    {
      "title": "Why Is Metaplanet Stock Down 25% Despite Bitcoin’s Rally?",
      "link": "https://cryptopanic.com/news/22052102/Why-Is-Metaplanet-Stock-Down-25-Despite-Bitcoins-Rally?mtm_campaign=API-OFA",
      "pubDate": "2025-05-24T06:14:14.000Z",
      "source": "Historical",
      "sourceKey": "historical",
      "category": "bitcoin",
      "description": "NULL",
      "currencies": [
        "BTC"
      ]
    },
    {
      "title": "Why Solaxy and Pepeto Are the Fastest Growing Cryptocurrencies? What It Means for XRP Price and XRP News",
      "link": "https://cryptopanic.com/news/22051849/Why-Solaxy-and-Pepeto-Are-the-Fastest-Growing-Cryptocurrencies-What-It-Means-for-XRP-Price-and-XRP-News?mtm_campaign=API-OFA",
      "pubDate": "2025-05-24T06:11:42.000Z",
      "source": "Historical",
      "sourceKey": "historical",
      "category": "trading",
      "description": "NULL",
      "currencies": [
        "XRP"
      ]
    },
    {
      "title": "Pi Network Launches Perpetual Futures on Kraken with 20x Leverage for U.S. Traders",
      "link": "https://cryptopanic.com/news/22051687/Pi-Network-Launches-Perpetual-Futures-on-Kraken-with-20x-Leverage-for-US-Traders?mtm_campaign=API-OFA",
      "pubDate": "2025-05-24T06:08:22.000Z",
      "source": "Historical",
      "sourceKey": "historical",
      "category": "exchange",
      "description": "NULL",
      "currencies": [
        "PI"
      ]
    },
    {
      "title": "Elon Musk’s DOGE Shares Plans To Avoid US Recession",
      "link": "https://cryptopanic.com/news/22051556/Elon-Musks-DOGE-Shares-Plans-To-Avoid-US-Recession?mtm_campaign=API-OFA",
      "pubDate": "2025-05-24T06:06:07.000Z",
      "source": "Historical",
      "sourceKey": "historical",
      "category": "altcoin",
      "description": "NULL",
      "currencies": [
        "DOGE"
      ]
    },
    {
      "title": "Litecoin Monthly Close Above Key Resistance Could Ignite 30% Rally – Is A Breakout Coming?",
      "link": "https://cryptopanic.com/news/22051325/Litecoin-Monthly-Close-Above-Key-Resistance-Could-Ignite-30-Rally-Is-A-Breakout-Coming?mtm_campaign=API-OFA",
      "pubDate": "2025-05-24T06:00:18.000Z",
      "source": "Historical",
      "sourceKey": "historical",
      "category": "trading",
      "description": "NULL",
      "currencies": [
        "BTC",
        "LTC"
      ]
    },
    {
      "title": "MOODENG, MEW crypto pump after Robinhood listing – What’s next?",
      "link": "https://cryptopanic.com/news/22051457/MOODENG-MEW-crypto-pump-after-Robinhood-listing-Whats-next?mtm_campaign=API-OFA",
      "pubDate": "2025-05-24T06:00:04.000Z",
      "source": "Historical",
      "sourceKey": "historical",
      "category": "trading",
      "description": "NULL",
      "currencies": [
        "MEW",
        "MEME",
        "MOODENG"
      ]
    },
    {
      "title": "Decentralized AI and the future of Web3: Exclusive Interview with DFINITY on the Internet Computer Vision",
      "link": "https://cryptopanic.com/news/internet-computer/22052101/Decentralized-AI-and-the-future-of-Web3-Exclusive-Interview-with-DFINITY-on-the-Internet-Computer-Vision",
      "pubDate": "2025-05-24T06:00:00.000Z",
      "source": "Historical",
      "sourceKey": "historical",
      "category": "general",
      "description": "NULL",
      "currencies": [
        "ICP",
        "Z"
      ]
    },
    {
      "title": "Trump Allegedly Uses Presidential Seal at Private Crypto Event",
      "link": "https://cryptopanic.com/news/22051334/Trump-Allegedly-Uses-Presidential-Seal-at-Private-Crypto-Event?mtm_campaign=API-OFA",
      "pubDate": "2025-05-24T05:56:21.000Z",
      "source": "Historical",
      "sourceKey": "historical",
      "category": "general",
      "description": "NULL",
      "currencies": [
        "TRUMP"
      ]
    },
    {
      "title": "Pi Network Ecosystem Grows with New Tools & Apps",
      "link": "https://cryptopanic.com/news/22053060/Pi-Network-Ecosystem-Grows-with-New-Tools-Apps?mtm_campaign=API-OFA",
      "pubDate": "2025-05-24T05:45:00.000Z",
      "source": "Historical",
      "sourceKey": "historical",
      "category": "general",
      "description": "NULL",
      "currencies": [
        "PI"
      ]
    },
    {
      "title": "Crypto Markets Shed Over $100 Billion After Trump’s Latest Tariff Threats (Weekend Watch)",
      "link": "https://cryptopanic.com/news/22051309/Crypto-Markets-Shed-Over-100-Billion-After-Trumps-Latest-Tariff-Threats-Weekend-Watch?mtm_campaign=API-OFA",
      "pubDate": "2025-05-24T05:42:55.000Z",
      "source": "Historical",
      "sourceKey": "historical",
      "category": "general",
      "description": "NULL",
      "currencies": [
        "USDT",
        "WIF",
        "ENA",
        "BTCUSD"
      ]
    },
    {
      "title": "Bitcoin Bull Run Could Last Until 2027, Says Top Crypto Analyst",
      "link": "https://cryptopanic.com/news/22051302/Bitcoin-Bull-Run-Could-Last-Until-2027-Says-Top-Crypto-Analyst?mtm_campaign=API-OFA",
      "pubDate": "2025-05-24T05:41:44.000Z",
      "source": "Historical",
      "sourceKey": "historical",
      "category": "bitcoin",
      "description": "NULL",
      "currencies": [
        "BTC"
      ],
      "votes": {
        "positive": 1,
        "negative": 0
      },
      "sentiment": "bullish"
    },
    {
      "title": "Why is Bitcoin Price Dropping Now? Will BTC Price Go Down to $100K?",
      "link": "https://cryptopanic.com/news/22051300/Why-is-Bitcoin-Price-Dropping-Now-Will-BTC-Price-Go-Down-to-100K?mtm_campaign=API-OFA",
      "pubDate": "2025-05-24T05:40:09.000Z",
      "source": "Historical",
      "sourceKey": "historical",
      "category": "bitcoin",
      "description": "NULL",
      "currencies": [
        "BTC",
        "ETH"
      ]
    },
    {
      "title": "Generations Betrayed: Why People Are Turning to Gold and Bitcoin",
      "link": "https://cryptopanic.com/news/22051292/Generations-Betrayed-Why-People-Are-Turning-to-Gold-and-Bitcoin?mtm_campaign=API-OFA",
      "pubDate": "2025-05-24T05:30:55.000Z",
      "source": "Historical",
      "sourceKey": "historical",
      "category": "bitcoin",
      "description": "NULL",
      "currencies": [
        "BTC"
      ]
    },
    {
      "title": "Massachusetts Bitcoin Launderer Sentenced to 6-Year Prison Term",
      "link": "https://cryptopanic.com/news/22051286/Massachusetts-Bitcoin-Launderer-Sentenced-to-6-Year-Prison-Term?mtm_campaign=API-OFA",
      "pubDate": "2025-05-24T05:23:17.000Z",
      "source": "Historical",
      "sourceKey": "historical",
      "category": "bitcoin",
      "description": "NULL",
      "currencies": [
        "BTC"
      ]
    },
    {
      "title": "Bitcoin ETFs post $2.75B in weekly inflows as price sits above $108K",
      "link": "https://cryptopanic.com/news/22051285/Bitcoin-ETFs-post-275B-in-weekly-inflows-as-price-sits-above-108K?mtm_campaign=API-OFA",
      "pubDate": "2025-05-24T05:21:16.000Z",
      "source": "Historical",
      "sourceKey": "historical",
      "category": "bitcoin",
      "description": "NULL",
      "currencies": [
        "BTC"
      ]
    },
    {
      "title": "BarriC predicts $20 XRP surge despite volatility: Is sub-$3 still a bargain?",
      "link": "https://cryptopanic.com/news/22051249/BarriC-predicts-20-XRP-surge-despite-volatility-Is-sub-3-still-a-bargain?mtm_campaign=API-OFA",
      "pubDate": "2025-05-24T05:14:38.000Z",
      "source": "Historical",
      "sourceKey": "historical",
      "category": "trading",
      "description": "NULL",
      "currencies": [
        "XRP"
      ]
    },
    {
      "title": "Significant Outflows from Major Investment Funds Reported",
      "link": "https://cryptopanic.com/news/22051279/Significant-Outflows-from-Major-Investment-Funds-Reported?mtm_campaign=API-OFA",
      "pubDate": "2025-05-24T05:14:36.000Z",
      "source": "Historical",
      "sourceKey": "historical",
      "category": "general",
      "description": "NULL",
      "currencies": [
        "ARK",
        "FBTC"
      ]
    },
    {
      "title": "DDC Enterprise Expands Bitcoin Holdings as Part of Reserve Strategy",
      "link": "https://cryptopanic.com/news/22051278/DDC-Enterprise-Expands-Bitcoin-Holdings-as-Part-of-Reserve-Strategy?mtm_campaign=API-OFA",
      "pubDate": "2025-05-24T05:14:05.000Z",
      "source": "Historical",
      "sourceKey": "historical",
      "category": "bitcoin",
      "description": "NULL",
      "currencies": [
        "BTC"
      ]
    },
    {
      "title": "Mantix Launches Presale Set To Go Viral As Hyperliquid & DYDX Face Tough Competition",
      "link": "https://cryptopanic.com/news/22051250/Mantix-Launches-Presale-Set-To-Go-Viral-As-Hyperliquid-DYDX-Face-Tough-Competition?mtm_campaign=API-OFA",
      "pubDate": "2025-05-24T05:13:50.000Z",
      "source": "Historical",
      "sourceKey": "historical",
      "category": "general",
      "description": "NULL",
      "currencies": [
        "DYDX",
        "HYPE"
      ]
    },
    {
      "title": "Polygon Co-Founder Mihailo Bjelic Steps Down Amid Industry Shifts",
      "link": "https://cryptopanic.com/news/22051277/Polygon-Co-Founder-Mihailo-Bjelic-Steps-Down-Amid-Industry-Shifts?mtm_campaign=API-OFA",
      "pubDate": "2025-05-24T05:13:36.000Z",
      "source": "Historical",
      "sourceKey": "historical",
      "category": "layer2",
      "description": "NULL",
      "currencies": [
        "ETH"
      ]
    },
    {
      "title": "U.S. President Trump Faces Legal Scrutiny Over Presidential Seal Usage at Private Event",
      "link": "https://cryptopanic.com/news/22051276/US-President-Trump-Faces-Legal-Scrutiny-Over-Presidential-Seal-Usage-at-Private-Event?mtm_campaign=API-OFA",
      "pubDate": "2025-05-24T05:12:17.000Z",
      "source": "Historical",
      "sourceKey": "historical",
      "category": "regulation",
      "description": "NULL",
      "currencies": [
        "TRUMP"
      ]
    },
    {
      "title": "XRP Price Prediction For May 24",
      "link": "https://cryptopanic.com/news/22050912/XRP-Price-Prediction-For-May-24?mtm_campaign=API-OFA",
      "pubDate": "2025-05-24T05:02:17.000Z",
      "source": "Historical",
      "sourceKey": "historical",
      "category": "trading",
      "description": "NULL",
      "currencies": [
        "XRP"
      ]
    },
    {
      "title": "dogwifhat: Whales loading, retail fading – Should you buy WIF’s dip?",
      "link": "https://cryptopanic.com/news/22050890/dogwifhat-Whales-loading-retail-fading-Should-you-buy-WIFs-dip?mtm_campaign=API-OFA",
      "pubDate": "2025-05-24T05:00:52.000Z",
      "source": "Historical",
      "sourceKey": "historical",
      "category": "general",
      "description": "NULL",
      "currencies": [
        "WIF",
        "MEME"
      ]
    },
    {
      "title": "VanEck strikes back against SEC’s silence on Bitcoin ETF",
      "link": "https://cryptopanic.com/news/22051005/VanEck-strikes-back-against-SECs-silence-on-Bitcoin-ETF?mtm_campaign=API-OFA",
      "pubDate": "2025-05-24T05:00:51.000Z",
      "source": "Historical",
      "sourceKey": "historical",
      "category": "bitcoin",
      "description": "NULL",
      "currencies": [
        "BTC"
      ]
    },
    {
      "title": "Semler Scientific Expands Bitcoin Holdings with $50M Purchase",
      "link": "https://cryptopanic.com/news/22052203/Semler-Scientific-Expands-Bitcoin-Holdings-with-50M-Purchase?mtm_campaign=API-OFA",
      "pubDate": "2025-05-24T05:00:00.000Z",
      "source": "Historical",
      "sourceKey": "historical",
      "category": "bitcoin",
      "description": "NULL",
      "currencies": [
        "BTC"
      ]
    },
    {
      "title": "Kalshi Enables Solana Deposits with Instant Cash Conversion, Expands Crypto Support, and Faces Polymarket Competition",
      "link": "https://cryptopanic.com/news/22050789/Kalshi-Enables-Solana-Deposits-with-Instant-Cash-Conversion-Expands-Crypto-Support-and-Faces-Polymarket-Competition?mtm_campaign=API-OFA",
      "pubDate": "2025-05-24T04:35:18.000Z",
      "source": "Historical",
      "sourceKey": "historical",
      "category": "altcoin",
      "description": "NULL",
      "currencies": [
        "SOL"
      ]
    },
    {
      "title": "Buy XRP Before It Explodes To $1,000, Market Expert Says",
      "link": "https://cryptopanic.com/news/22050784/Buy-XRP-Before-It-Explodes-To-1000-Market-Expert-Says?mtm_campaign=API-OFA",
      "pubDate": "2025-05-24T04:30:52.000Z",
      "source": "Historical",
      "sourceKey": "historical",
      "category": "altcoin",
      "description": "NULL",
      "currencies": [
        "BTC",
        "XRP"
      ]
    },
    {
      "title": "AI Crypto Coins All Set to Explode in June 2025",
      "link": "https://cryptopanic.com/news/22050785/AI-Crypto-Coins-All-Set-to-Explode-in-June-2025?mtm_campaign=API-OFA",
      "pubDate": "2025-05-24T04:30:48.000Z",
      "source": "Historical",
      "sourceKey": "historical",
      "category": "general",
      "description": "NULL",
      "currencies": [
        "AGIX"
      ]
    },
    {
      "title": "Analyst Sets XRP Price Target at $11 This Bull Cycle",
      "link": "https://cryptopanic.com/news/22051295/Analyst-Sets-XRP-Price-Target-at-11-This-Bull-Cycle?mtm_campaign=API-OFA",
      "pubDate": "2025-05-24T04:29:00.000Z",
      "source": "Historical",
      "sourceKey": "historical",
      "category": "trading",
      "description": "NULL",
      "currencies": [
        "XRP"
      ]
    },
    {
      "title": "How will a Bitcoin Price Temperature of 2.67 affect BTC’s future?",
      "link": "https://cryptopanic.com/news/22050480/How-will-a-Bitcoin-Price-Temperature-of-267-affect-BTCs-future?mtm_campaign=API-OFA",
      "pubDate": "2025-05-24T04:00:27.000Z",
      "source": "Historical",
      "sourceKey": "historical",
      "category": "bitcoin",
      "description": "NULL",
      "currencies": [
        "BTC"
      ]
    },
    {
      "title": "Metaplanet Tops Japan Trading with 158.8M Shares, ¥132B Volume Before Stock Hits Stop Loss Amid Bitcoin Drop",
      "link": "https://cryptopanic.com/news/22050308/Metaplanet-Tops-Japan-Trading-with-1588M-Shares-132B-Volume-Before-Stock-Hits-Stop-Loss-Amid-Bitcoin-Drop?mtm_campaign=API-OFA",
      "pubDate": "2025-05-24T03:35:18.000Z",
      "source": "Historical",
      "sourceKey": "historical",
      "category": "bitcoin",
      "description": "NULL",
      "currencies": [
        "BTC"
      ]
    },
    {
      "title": "Stealth Bitcoin Bull Run Ahead: Fidelity Says Do Not Blink",
      "link": "https://cryptopanic.com/news/22050294/Stealth-Bitcoin-Bull-Run-Ahead-Fidelity-Says-Do-Not-Blink?mtm_campaign=API-OFA",
      "pubDate": "2025-05-24T03:30:59.000Z",
      "source": "Historical",
      "sourceKey": "historical",
      "category": "bitcoin",
      "description": "NULL",
      "currencies": [
        "BTC",
        "IP"
      ]
    },
    {
      "title": "Texas Awaits Governor's Nod for Bitcoin Reserve Bill",
      "link": "https://cryptopanic.com/news/22050277/Texas-Awaits-Governors-Nod-for-Bitcoin-Reserve-Bill?mtm_campaign=API-OFA",
      "pubDate": "2025-05-24T03:25:34.000Z",
      "source": "Historical",
      "sourceKey": "historical",
      "category": "bitcoin",
      "description": "NULL",
      "currencies": [
        "BTC"
      ]
    },
    {
      "title": "Fold Unveils Bitcoin Gift Card for Retail Use",
      "link": "https://cryptopanic.com/news/22047335/Fold-Unveils-Bitcoin-Gift-Card-for-Retail-Use?mtm_campaign=API-OFA",
      "pubDate": "2025-05-24T03:01:56.000Z",
      "source": "Historical",
      "sourceKey": "historical",
      "category": "bitcoin",
      "description": "NULL",
      "currencies": [
        "BTC"
      ]
    },
    {
      "title": "Injective leads AI token surge with 12% rise – Is $17 possible for INJ?",
      "link": "https://cryptopanic.com/news/22049854/Injective-leads-AI-token-surge-with-12-rise-Is-17-possible-for-INJ?mtm_campaign=API-OFA",
      "pubDate": "2025-05-24T03:00:54.000Z",
      "source": "Historical",
      "sourceKey": "historical",
      "category": "trading",
      "description": "NULL",
      "currencies": [
        "INJ"
      ]
    },
    {
      "title": "Pi Network Expands Ecosystem and Boosts Security with 2 New Updates",
      "link": "https://cryptopanic.com/news/22049859/Pi-Network-Expands-Ecosystem-and-Boosts-Security-with-2-New-Updates?mtm_campaign=API-OFA",
      "pubDate": "2025-05-24T03:00:50.000Z",
      "source": "Historical",
      "sourceKey": "historical",
      "category": "regulation",
      "description": "NULL",
      "currencies": [
        "PI"
      ]
    },
    {
      "title": "BlockDAG’s Double BDAG Offer Fuels $264M Presale Explosion! ETH Struggles at $2,700 & XRP Stalls at $2.45",
      "link": "https://cryptopanic.com/news/22049732/BlockDAGs-Double-BDAG-Offer-Fuels-264M-Presale-Explosion-ETH-Struggles-at-2700-XRP-Stalls-at-245?mtm_campaign=API-OFA",
      "pubDate": "2025-05-24T03:00:00.000Z",
      "source": "Historical",
      "sourceKey": "historical",
      "category": "ethereum",
      "description": "NULL",
      "currencies": [
        "ETH",
        "XRP"
      ]
    },
    {
      "title": "BTFD Coin’s $7.14M Presale and 12,400+ Bulls Community Secure Its Spot Among the 5 Top New Meme Coins to Join Today With GOAT and SNEK",
      "link": "https://cryptopanic.com/news/22049708/BTFD-Coins-714M-Presale-and-12400-Bulls-Community-Secure-Its-Spot-Among-the-5-Top-New-Meme-Coins-to-Join-Today-With-GOAT-and-SNEK?mtm_campaign=API-OFA",
      "pubDate": "2025-05-24T02:45:00.000Z",
      "source": "Historical",
      "sourceKey": "historical",
      "category": "trading",
      "description": "NULL",
      "currencies": [
        "BTC",
        "SNEK",
        "GOAT"
      ]
    },
    {
      "title": "Bitcoin and Ethereum ETFs See $1 Billion in One Day",
      "link": "https://cryptopanic.com/news/22049731/Bitcoin-and-Ethereum-ETFs-See-1-Billion-in-One-Day?mtm_campaign=API-OFA",
      "pubDate": "2025-05-24T02:44:26.000Z",
      "source": "Historical",
      "sourceKey": "historical",
      "category": "bitcoin",
      "description": "NULL",
      "currencies": [
        "BTC",
        "ETH",
        "BTCUSD"
      ]
    },
    {
      "title": "CZ Slams WSJ for Claiming He Helped Trump-Linked Crypto Deal",
      "link": "https://cryptopanic.com/news/22049707/CZ-Slams-WSJ-for-Claiming-He-Helped-Trump-Linked-Crypto-Deal?mtm_campaign=API-OFA",
      "pubDate": "2025-05-24T02:42:02.000Z",
      "source": "Historical",
      "sourceKey": "historical",
      "category": "general",
      "description": "NULL",
      "currencies": [
        "BTC",
        "IP",
        "BTCUSD"
      ]
    },
    {
      "title": "Whale Activity: Significant AAVE Purchase Follows WBTC Sale",
      "link": "https://cryptopanic.com/news/22051273/Whale-Activity-Significant-AAVE-Purchase-Follows-WBTC-Sale?mtm_campaign=API-OFA",
      "pubDate": "2025-05-24T02:33:37.000Z",
      "source": "Historical",
      "sourceKey": "historical",
      "category": "bitcoin",
      "description": "NULL",
      "currencies": [
        "WBTC",
        "AAVE"
      ]
    },
    {
      "title": "Bitcoin Extreme Greed Is Here—Time To Be A Contrarian?",
      "link": "https://cryptopanic.com/news/22049667/Bitcoin-Extreme-Greed-Is-HereTime-To-Be-A-Contrarian?mtm_campaign=API-OFA",
      "pubDate": "2025-05-24T02:30:08.000Z",
      "source": "Historical",
      "sourceKey": "historical",
      "category": "bitcoin",
      "description": "NULL",
      "currencies": [
        "BTC",
        "USDT"
      ]
    },
    {
      "title": "Can TAO Crypto Lead New AI Coins Season?",
      "link": "https://cryptopanic.com/news/22049666/Can-TAO-Crypto-Lead-New-AI-Coins-Season?mtm_campaign=API-OFA",
      "pubDate": "2025-05-24T02:29:30.000Z",
      "source": "Historical",
      "sourceKey": "historical",
      "category": "general",
      "description": "NULL",
      "currencies": [
        "BTC",
        "TAO"
      ]
    },
    {
      "title": "Collaterize Crypto Made an ATH, Facing Pullback: Dips To Buy?",
      "link": "https://cryptopanic.com/news/22049665/Collaterize-Crypto-Made-an-ATH-Facing-Pullback-Dips-To-Buy?mtm_campaign=API-OFA",
      "pubDate": "2025-05-24T02:24:40.000Z",
      "source": "Historical",
      "sourceKey": "historical",
      "category": "general",
      "description": "NULL",
      "currencies": [
        "ATH",
        "RWA",
        "COLLAT"
      ]
    },
    {
      "title": "Tron Price Analysis: TRX Halts Below $0.30 as Justin Sun Attends Trump Dinner",
      "link": "https://cryptopanic.com/news/22049660/Tron-Price-Analysis-TRX-Halts-Below-030-as-Justin-Sun-Attends-Trump-Dinner?mtm_campaign=API-OFA",
      "pubDate": "2025-05-24T02:20:36.000Z",
      "source": "Historical",
      "sourceKey": "historical",
      "category": "trading",
      "description": "NULL",
      "currencies": [
        "TRX"
      ]
    },
    {
      "title": "VeChain VET Price In An Uptrend – Structure Remains Bullish",
      "link": "https://cryptopanic.com/news/22049664/VeChain-VET-Price-In-An-Uptrend-Structure-Remains-Bullish?mtm_campaign=API-OFA",
      "pubDate": "2025-05-24T02:19:04.000Z",
      "source": "Historical",
      "sourceKey": "historical",
      "category": "trading",
      "description": "NULL",
      "currencies": [
        "VET"
      ]
    },
    {
      "title": "Tron Founder Justin Sun’s $75M Trump Token Bet Raises Eyebrows",
      "link": "https://cryptopanic.com/news/22051261/Tron-Founder-Justin-Suns-75M-Trump-Token-Bet-Raises-Eyebrows?mtm_campaign=API-OFA",
      "pubDate": "2025-05-24T02:19:00.000Z",
      "source": "Historical",
      "sourceKey": "historical",
      "category": "general",
      "description": "NULL",
      "currencies": [
        "TRX",
        "TRUMP"
      ]
    },
    {
      "title": "Semler Scientific Buys Additional 455 BTC, Now Holds Over $474M in Bitcoin",
      "link": "https://cryptopanic.com/news/22049631/Semler-Scientific-Buys-Additional-455-BTC-Now-Holds-Over-474M-in-Bitcoin?mtm_campaign=API-OFA",
      "pubDate": "2025-05-24T02:16:53.000Z",
      "source": "Historical",
      "sourceKey": "historical",
      "category": "bitcoin",
      "description": "NULL",
      "currencies": [
        "BTC"
      ]
    },
    {
      "title": "CME launches XRP futures as Ripple pushes for U.S. crypto leadership post-SEC victory",
      "link": "https://cryptopanic.com/news/22049616/CME-launches-XRP-futures-as-Ripple-pushes-for-US-crypto-leadership-post-SEC-victory?mtm_campaign=API-OFA",
      "pubDate": "2025-05-24T02:15:52.000Z",
      "source": "Historical",
      "sourceKey": "historical",
      "category": "regulation",
      "description": "NULL",
      "currencies": [
        "BTC",
        "ETH",
        "XRP"
      ]
    },
    {
      "title": "Tesla’s Bitcoin holdings hit $1.25 billion as BTC surge validates crypto strategy",
      "link": "https://cryptopanic.com/news/22049491/Teslas-Bitcoin-holdings-hit-125-billion-as-BTC-surge-validates-crypto-strategy?mtm_campaign=API-OFA",
      "pubDate": "2025-05-24T02:07:03.000Z",
      "source": "Historical",
      "sourceKey": "historical",
      "category": "bitcoin",
      "description": "NULL",
      "currencies": [
        "BTC"
      ]
    },
    {
      "title": "Polygon co-founder steps down, will be &#039;cheering from the sidelines&#039;",
      "link": "https://cryptopanic.com/news/22049264/Polygon-co-founder-steps-down-will-be-039cheering-from-the-sidelines039?mtm_campaign=API-OFA",
      "pubDate": "2025-05-24T02:01:39.000Z",
      "source": "Historical",
      "sourceKey": "historical",
      "category": "layer2",
      "description": "NULL",
      "currencies": [
        "ETH"
      ]
    },
    {
      "title": "PEPE surges 14% on 200% whale spike – Is this just another retail FOMO surge?",
      "link": "https://cryptopanic.com/news/22049115/PEPE-surges-14-on-200-whale-spike-Is-this-just-another-retail-FOMO-surge?mtm_campaign=API-OFA",
      "pubDate": "2025-05-24T02:00:22.000Z",
      "source": "Historical",
      "sourceKey": "historical",
      "category": "trading",
      "description": "NULL",
      "currencies": [
        "PEPE",
        "MEME"
      ]
    },
    {
      "title": "Bitcoin’s All-Time High Spurs Global Corporate Adoption Across Sectors",
      "link": "https://cryptopanic.com/news/22049706/Bitcoins-All-Time-High-Spurs-Global-Corporate-Adoption-Across-Sectors?mtm_campaign=API-OFA",
      "pubDate": "2025-05-24T02:00:00.000Z",
      "source": "Historical",
      "sourceKey": "historical",
      "category": "bitcoin",
      "description": "NULL",
      "currencies": [
        "BTC",
        "ATH"
      ]
    },
    {
      "title": "Tether charts its own path beyond U.S. borders",
      "link": "https://cryptopanic.com/news/22049111/Tether-charts-its-own-path-beyond-US-borders?mtm_campaign=API-OFA",
      "pubDate": "2025-05-24T01:46:17.000Z",
      "source": "Historical",
      "sourceKey": "historical",
      "category": "ethereum",
      "description": "NULL",
      "currencies": [
        "USDT"
      ]
    },
    {
      "title": "Trump: US Is Dominating in Crypto and Bitcoin—‘We Will Keep It That Way’",
      "link": "https://cryptopanic.com/news/22050290/Trump-US-Is-Dominating-in-Crypto-and-BitcoinWe-Will-Keep-It-That-Way?mtm_campaign=API-OFA",
      "pubDate": "2025-05-24T01:30:37.000Z",
      "source": "Historical",
      "sourceKey": "historical",
      "category": "bitcoin",
      "description": "NULL",
      "currencies": [
        "BTC",
        "TRUMP"
      ]
    },
    {
      "title": "WalletConnect Expands to Solana, Launches WCT Token with 5M Token Airdrop",
      "link": "https://cryptopanic.com/news/22049067/WalletConnect-Expands-to-Solana-Launches-WCT-Token-with-5M-Token-Airdrop?mtm_campaign=API-OFA",
      "pubDate": "2025-05-24T01:30:29.000Z",
      "source": "Historical",
      "sourceKey": "historical",
      "category": "altcoin",
      "description": "NULL",
      "currencies": [
        "ETH",
        "SOL",
        "WCT"
      ]
    },
    {
      "title": "Why is XRP Price Down Today: Ripple’s $300M RLUSD Market Rattled as JP Morgan Partners 3 US Banks for “Wall Street Stablecoin”",
      "link": "https://cryptopanic.com/news/22049066/Why-is-XRP-Price-Down-Today-Ripples-300M-RLUSD-Market-Rattled-as-JP-Morgan-Partners-3-US-Banks-for-Wall-Street-Stablecoin?mtm_campaign=API-OFA",
      "pubDate": "2025-05-24T01:26:05.000Z",
      "source": "Historical",
      "sourceKey": "historical",
      "category": "trading",
      "description": "NULL",
      "currencies": [
        "BTC",
        "XRP",
        "RLUSD"
      ]
    },
    {
      "title": "Tesla's Bitcoin Holdings Reach $1.24 Billion in Value",
      "link": "https://cryptopanic.com/news/22051271/Teslas-Bitcoin-Holdings-Reach-124-Billion-in-Value?mtm_campaign=API-OFA",
      "pubDate": "2025-05-24T01:13:46.000Z",
      "source": "Historical",
      "sourceKey": "historical",
      "category": "bitcoin",
      "description": "NULL",
      "currencies": [
        "BTC"
      ]
    },
    {
      "title": "Bitcoin Ownership Among Americans Surpasses Gold, U.S. Outpaces China with 40% of Bitcoin and Federal Holdings Double Gold Market Share",
      "link": "https://cryptopanic.com/news/22048907/Bitcoin-Ownership-Among-Americans-Surpasses-Gold-US-Outpaces-China-with-40-of-Bitcoin-and-Federal-Holdings-Double-Gold-Market-Share?mtm_campaign=API-OFA",
      "pubDate": "2025-05-24T01:05:18.000Z",
      "source": "Historical",
      "sourceKey": "historical",
      "category": "bitcoin",
      "description": "NULL",
      "currencies": [
        "BTC"
      ]
    },
    {
      "title": "BNB Price Slingshot To $1,000: Why The 50 EMA Could Hold The Key",
      "link": "https://cryptopanic.com/news/22048577/BNB-Price-Slingshot-To-1000-Why-The-50-EMA-Could-Hold-The-Key?mtm_campaign=API-OFA",
      "pubDate": "2025-05-24T01:00:34.000Z",
      "source": "Historical",
      "sourceKey": "historical",
      "category": "trading",
      "description": "NULL",
      "currencies": [
        "BNB",
        "CLOUD",
        "WISE"
      ]
    },
    {
      "title": "Ethereum holds $2,370 support, but whale activity warns of…",
      "link": "https://cryptopanic.com/news/22048752/Ethereum-holds-2370-support-but-whale-activity-warns-of?mtm_campaign=API-OFA",
      "pubDate": "2025-05-24T01:00:24.000Z",
      "source": "Historical",
      "sourceKey": "historical",
      "category": "ethereum",
      "description": "NULL",
      "currencies": [
        "ETH"
      ]
    },
    {
      "title": "COZ puts forth discussion to change GAS rewards for Neo governance",
      "link": "https://cryptopanic.com/news/22048566/COZ-puts-forth-discussion-to-change-GAS-rewards-for-Neo-governance?mtm_campaign=API-OFA",
      "pubDate": "2025-05-24T00:59:27.000Z",
      "source": "Historical",
      "sourceKey": "historical",
      "category": "general",
      "description": "NULL",
      "currencies": [
        "NEO"
      ]
    },
    {
      "title": "Bitcoin Bull Market Reshapes Investment Portfolio Position",
      "link": "https://cryptopanic.com/news/22051270/Bitcoin-Bull-Market-Reshapes-Investment-Portfolio-Position?mtm_campaign=API-OFA",
      "pubDate": "2025-05-24T00:53:48.000Z",
      "source": "Historical",
      "sourceKey": "historical",
      "category": "bitcoin",
      "description": "NULL",
      "currencies": [
        "BTC"
      ]
    },
    {
      "title": "Cryptocurrency Trader Adjusts Positions Amid Market Downturn",
      "link": "https://cryptopanic.com/news/22051269/Cryptocurrency-Trader-Adjusts-Positions-Amid-Market-Downturn?mtm_campaign=API-OFA",
      "pubDate": "2025-05-24T00:44:07.000Z",
      "source": "Historical",
      "sourceKey": "historical",
      "category": "general",
      "description": "NULL",
      "currencies": [
        "BTC",
        "ETH",
        "SUI"
      ]
    },
    {
      "title": "Texas Governor Supports Bitcoin Reserve Bill",
      "link": "https://cryptopanic.com/news/22051268/Texas-Governor-Supports-Bitcoin-Reserve-Bill?mtm_campaign=API-OFA",
      "pubDate": "2025-05-24T00:23:48.000Z",
      "source": "Historical",
      "sourceKey": "historical",
      "category": "bitcoin",
      "description": "NULL",
      "currencies": [
        "BTC"
      ]
    },
    {
      "title": "Will Bitcoin bulls secure $110K before BTC’s $13.8B options expiry?",
      "link": "https://cryptopanic.com/news/22048501/Will-Bitcoin-bulls-secure-110K-before-BTCs-138B-options-expiry?mtm_campaign=API-OFA",
      "pubDate": "2025-05-24T00:22:21.000Z",
      "source": "Historical",
      "sourceKey": "historical",
      "category": "bitcoin",
      "description": "NULL",
      "currencies": [
        "BTC"
      ]
    },
    {
      "title": "Whale Investor Faces Significant Losses Amid High-Leverage Bitcoin Position",
      "link": "https://cryptopanic.com/news/22051266/Whale-Investor-Faces-Significant-Losses-Amid-High-Leverage-Bitcoin-Position?mtm_campaign=API-OFA",
      "pubDate": "2025-05-24T00:13:40.000Z",
      "source": "Historical",
      "sourceKey": "historical",
      "category": "bitcoin",
      "description": "NULL",
      "currencies": [
        "BTC",
        "PEPE"
      ]
    },
    {
      "title": "Which Way Circle?",
      "link": "https://cryptopanic.com/news/22048098/Which-Way-Circle?mtm_campaign=API-OFA",
      "pubDate": "2025-05-24T00:03:05.000Z",
      "source": "Historical",
      "sourceKey": "historical",
      "category": "stablecoin",
      "description": "NULL",
      "currencies": [
        "SUI"
      ]
    },
    {
      "title": "Bitcoin (BTC): Post-ATH Crash Incoming? XRP on Verge of Major Trend Test Now, Solana's (SOL) $200 Surge Looms",
      "link": "https://cryptopanic.com/news/22048249/Bitcoin-BTC-Post-ATH-Crash-Incoming-XRP-on-Verge-of-Major-Trend-Test-Now-Solanas-SOL-200-Surge-Looms?mtm_campaign=API-OFA",
      "pubDate": "2025-05-24T00:01:00.000Z",
      "source": "Historical",
      "sourceKey": "historical",
      "category": "bitcoin",
      "description": "NULL",
      "currencies": [
        "BTC",
        "XRP",
        "SOL",
        "ATH"
      ]
    },
    {
      "title": "Best Crypto Right Now: Solana, Dogecoin, and XRP Push Forward, But BlockDAG’s $0.0020 Window Is Closing Fast",
      "link": "https://cryptopanic.com/news/22047915/Best-Crypto-Right-Now-Solana-Dogecoin-and-XRP-Push-Forward-But-BlockDAGs-00020-Window-Is-Closing-Fast?mtm_campaign=API-OFA",
      "pubDate": "2025-05-24T00:00:00.000Z",
      "source": "Historical",
      "sourceKey": "historical",
      "category": "altcoin",
      "description": "NULL",
      "currencies": [
        "XRP",
        "SOL",
        "DOGE"
      ]
    }
  ]
}